README.md
setup.py
petyr/__init__.py
petyr.egg-info/PKG-INFO
petyr.egg-info/SOURCES.txt
petyr.egg-info/dependency_links.txt
petyr.egg-info/requires.txt
petyr.egg-info/top_level.txt
tests/__init__.py
tests/test_affine.py
tests/test_homography.py
tests/test_similarity.py
tests/test_transform2d.py