Metadata-Version: 2.1
Name: petyr
Version: 0.0.8
Summary: Affine, Similarity Transformations and Homography for Python
Home-page: https://github.com/safwankdb/petyr
Author: Mohd Safwan
Author-email: kdbeatbox@gmail.com
License: UNKNOWN
Platform: UNKNOWN
Classifier: Programming Language :: Python :: 3
Classifier: License :: OSI Approved :: MIT License
Classifier: Operating System :: OS Independent
Requires-Python: >=3.6
